BaseNN/BaseNN.py
BaseNN/__init__.py
BaseNN/load_data.py
BaseNN/version.py
BaseNN/blocks/__init__.py
BaseNN/blocks/diffusion_unet.py
BaseNN/blocks/mobilenetv2.py
BaseNN/examples/BaseNN_demo.py
BaseNN/examples/__init__.py
BaseNN/examples/basenn_act.py
BaseNN/examples/basenn_cd.py
BaseNN/examples/basenn_iris.py
BaseNN/examples/basenn_mn.py
BaseNN/examples/basenn_tang.py
BaseNN/examples/gradio_demo.py
BaseNN/examples/pkl2pth.py
BaseNN/examples/rl_demo.py
BaseNN/examples/tran.py
BaseNN/examples/transformer_demo.py
BaseNN/examples/models/__init__.py
BaseNN/examples/models/blocks/__init__.py
BaseNN/examples/models/blocks/decoder_layer.py
BaseNN/examples/models/blocks/encoder_layer.py
BaseNN/examples/models/embedding/__init__.py
BaseNN/examples/models/embedding/positional_encoding.py
BaseNN/examples/models/embedding/token_embeddings.py
BaseNN/examples/models/embedding/transformer_embedding.py
BaseNN/examples/models/layers/__init__.py
BaseNN/examples/models/layers/layer_norm.py
BaseNN/examples/models/layers/multi_head_attention.py
BaseNN/examples/models/layers/position_wise_feed_forward.py
BaseNN/examples/models/layers/scale_dot_product_attention.py
BaseNN/examples/models/model/__init__.py
BaseNN/examples/models/model/decoder.py
BaseNN/examples/models/model/encoder.py
BaseNN/examples/models/model/transformer.py
basenn-2.0.0.dist-info/METADATA
basenn-2.0.0.dist-info/WHEEL
basenn-2.0.0.dist-info/entry_points.txt
basenn-2.0.0.dist-info/top_level.txt
basenn-2.0.0.dist-info/zip-safe
basenn-2.0.0.dist-info/RECORD
