Metadata-Version: 2.1
Name: BaseNN
Version: 2.0.0
Summary: BaseNN can easily build neural networks layer by layer and deeply explore the neural network principle.
Home-page: https://github.com/XEduPro/OpenBaseLab-Edu
Author: XEduPro
Author-email: easonqys@foxmail.com
License: MIT License
Requires-Python: >=3.6
